pysportsref/__init__.py
pysportsref/parsing.py
pysportsref/scraping.py
pysportsref/stats.py
pysportsref/transform.py
pysportsref/basketball/__init__.py
pysportsref/basketball/table_names.py
pysportsref/basketball/url_formats.py
pysportsref/football/__init__.py
pysportsref/football/table_names.py
pysportsref/football/url_formats.py
pysportsref/integration_tests/__init__.py
pysportsref/integration_tests/test_scraper.py
pysportsref/unit_tests/__init__.py
pysportsref/unit_tests/test_parsing.py
pysportsref/unit_tests/test_stats.py
pysportsref/unit_tests/test_transform.py
sports_ref/__init__.py
sports_ref/parsing.py
sports_ref/scraping.py
sports_ref/transform.py
sports_ref/basketball_ref/__init__.py
sports_ref/basketball_ref/table_names.py
sports_ref/basketball_ref/url_formats.py
sports_ref/integration_tests/__init__.py
sports_ref/integration_tests/test_scraper.py
sports_ref/unit_tests/__init__.py
sports_ref/unit_tests/test_parsing.py
sports_ref/unit_tests/test_transform.py
pysportsref-0.0.2.dist-info/LICENSE
pysportsref-0.0.2.dist-info/METADATA
pysportsref-0.0.2.dist-info/WHEEL
pysportsref-0.0.2.dist-info/top_level.txt
pysportsref-0.0.2.dist-info/RECORD
