Metadata-Version: 2.1
Name: pysportsref
Version: 0.0.2
Summary: Utilities for working with Sports Reference
Home-page: https://github.com/hwchase17/pysportsref
License: MIT
Platform: UNKNOWN
Requires-Dist: bs4
Requires-Dist: numpy
Requires-Dist: pandas
Requires-Dist: requests
Requires-Dist: lxml
Requires-Dist: tqdm
